LICENSE
README.rst
setup.py
hello_world/__init__.py
hello_world/main.py
hello_world_bw_test.egg-info/PKG-INFO
hello_world_bw_test.egg-info/SOURCES.txt
hello_world_bw_test.egg-info/dependency_links.txt
hello_world_bw_test.egg-info/top_level.txt